qcanvas/__init__.py
qcanvas/app.py
qcanvas/backend_connectors/__init__.py
qcanvas/backend_connectors/frontend_resource_manager.py
qcanvas/backend_connectors/qcanvas_task_master.py
qcanvas/icons/__init__.py
qcanvas/icons/_icon_type.py
qcanvas/icons/icons.qrc
qcanvas/icons/rc_icons.py
qcanvas/settings/__init__.py
qcanvas/settings/_client_settings.py
qcanvas/settings/_course_settings.py
qcanvas/settings/_mapped_setting.py
qcanvas/settings/_ui_settings.py
qcanvas/theme.py
qcanvas/ui/__init__.py
qcanvas/ui/course_viewer/__init__.py
qcanvas/ui/course_viewer/content_tree.py
qcanvas/ui/course_viewer/course_tree/__init__.py
qcanvas/ui/course_viewer/course_tree/_course_icon_generator.py
qcanvas/ui/course_viewer/course_tree/course_tree.py
qcanvas/ui/course_viewer/course_viewer.py
qcanvas/ui/course_viewer/tabs/__init__.py
qcanvas/ui/course_viewer/tabs/assignment_tab/__init__.py
qcanvas/ui/course_viewer/tabs/assignment_tab/assignment_tab.py
qcanvas/ui/course_viewer/tabs/assignment_tab/assignment_tree.py
qcanvas/ui/course_viewer/tabs/constants.py
qcanvas/ui/course_viewer/tabs/content_tab.py
qcanvas/ui/course_viewer/tabs/file_tab/__init__.py
qcanvas/ui/course_viewer/tabs/file_tab/file_tab.py
qcanvas/ui/course_viewer/tabs/file_tab/file_tree.py
qcanvas/ui/course_viewer/tabs/file_tab/pages_file_tree.py
qcanvas/ui/course_viewer/tabs/mail_tab/__init__.py
qcanvas/ui/course_viewer/tabs/mail_tab/mail_tab.py
qcanvas/ui/course_viewer/tabs/mail_tab/mail_tree.py
qcanvas/ui/course_viewer/tabs/page_tab/__init__.py
qcanvas/ui/course_viewer/tabs/page_tab/page_tab.py
qcanvas/ui/course_viewer/tabs/page_tab/page_tree.py
qcanvas/ui/course_viewer/tabs/resource_rich_browser.py
qcanvas/ui/course_viewer/tree_widget_data_item.py
qcanvas/ui/memory_tree/__init__.py
qcanvas/ui/memory_tree/_tree_memory.py
qcanvas/ui/memory_tree/memory_tree_widget.py
qcanvas/ui/memory_tree/memory_tree_widget_item.py
qcanvas/ui/qcanvas_window/__init__.py
qcanvas/ui/qcanvas_window/course_viewer_container.py
qcanvas-2026.1.20.dist-info/METADATA
qcanvas-2026.1.20.dist-info/WHEEL
qcanvas-2026.1.20.dist-info/entry_points.txt
qcanvas-2026.1.20.dist-info/RECORD
