Metadata-Version: 2.4
Name: qcanvas
Version: 2026.1.20
Summary: View courses from Canvas LMS
Author: QCanvas
Author-email: QCanvas@noreply.codeberg.org
Requires-Python: >=3.12,<3.13
Classifier: Development Status :: 5 - Production/Stable
Classifier: Environment :: X11 Applications
Classifier: Environment :: X11 Applications :: Qt
Classifier: Framework :: Pydantic
Classifier: Framework :: Pydantic :: 2
Classifier: Intended Audience :: Education
Classifier: Intended Audience :: End Users/Desktop
Classifier: License :: OSI Approved :: GNU Affero General Public License v3
Classifier: Natural Language :: English
Classifier: Operating System :: Microsoft :: Windows
Classifier: Operating System :: Microsoft :: Windows :: Windows 10
Classifier: Operating System :: Microsoft :: Windows :: Windows 11
Classifier: Operating System :: OS Independent
Classifier: Operating System :: POSIX :: Linux
Classifier: Programming Language :: Python
Classifier: Programming Language :: Python :: 3
Classifier: Programming Language :: Python :: 3.12
Classifier: Programming Language :: Python :: 3 :: Only
Classifier: Programming Language :: Python :: Implementation :: CPython
Classifier: Topic :: Database
Classifier: Topic :: Internet
Classifier: Topic :: Internet :: WWW/HTTP
Classifier: Topic :: Text Editors :: Text Processing
Classifier: Topic :: Text Processing :: Markup :: HTML
Classifier: Typing :: Typed
Requires-Dist: aiofile (>=3.9.0,<4.0.0)
Requires-Dist: aiosqlite (>=0.21.0,<0.22.0)
Requires-Dist: asynctaskpool (>=0.2.1,<0.3.0)
Requires-Dist: cachetools (>=6.2.4,<7.0.0)
Requires-Dist: libqcanvas (>=2026.1.20)
Requires-Dist: platformdirs (>=4.2.2,<5.0.0)
Requires-Dist: pyqtdarktheme-fork (>=2.3.2,<3.0.0)
Requires-Dist: qasync (>=0.28.0,<0.29.0)
Requires-Dist: sqlalchemy (>=2.0.45,<3.0.0)
Requires-Dist: validators (>=0.35.0,<0.36.0)
